PythonicBrain/PBDatetime.py
PythonicBrain/PBDecorators.py
PythonicBrain/PBInteger.py
PythonicBrain/PBMath.py
PythonicBrain/PBNetwork.py
PythonicBrain/PBString.py
PythonicBrain/PBTable.py
PythonicBrain/PBTools.py
PythonicBrain/__init__.py
PythonicBrain/Math/__init__.py
PythonicBrain/Math/plus.py
PythonicBrain/PBMath/Random.py
PythonicBrain/PBMath/__init__.py
PythonicBrain-0.0.3.dist-info/LICENSE
PythonicBrain-0.0.3.dist-info/METADATA
PythonicBrain-0.0.3.dist-info/WHEEL
PythonicBrain-0.0.3.dist-info/top_level.txt
PythonicBrain-0.0.3.dist-info/RECORD
