Metadata-Version: 2.1
Name: PythonicBrain
Version: 0.0.3
Summary: A python Util package 
Home-page: https://github.com/Ekbal41/PythoniBrain
Author: Asif Ekbal
Author-email: mdasifekbalshagor@gmail.com
Classifier: Programming Language :: Python :: 3
Classifier: Operating System :: OS Independent
Classifier: License :: OSI Approved :: MIT License
License-File: LICENSE
